{
    "pagination": "question",
    "lunaticModelVersion": "2.2.10",
    "modele": "TIME",
    "enoCoreVersion": "2.3.11",
    "generatingDate": "29-09-2022 13:56:00",
    "missing": false,
    "id": "l8lq5lp6",
    "label": "Time",
    "maxPage": "5",
    "variables": [
        {
            "variableType": "COLLECTED",
            "values": {
                "COLLECTED": null,
                "EDITED": null,
                "INPUTED": null,
                "FORCED": null,
                "PREVIOUS": null
            },
            "name": "FIRSTNAME",
            "componentRef": "inputtext_firstName"
        },
        {
            "variableType": "COLLECTED",
            "values": {
                "COLLECTED": null,
                "EDITED": null,
                "INPUTED": null,
                "FORCED": null,
                "PREVIOUS": null
            },
            "name": "SURVEYDATE",
            "componentRef": "datepicker_surveyDate"
        },
        {
            "variableType": "COLLECTED",
            "values": {
                "COLLECTED": [null],
                "EDITED": [null],
                "INPUTED": [null],
                "FORCED": [null],
                "PREVIOUS": [null]
            },
            "name": "STARTTIME",
            "componentRef": "timepicker_startTime"
        },
        {
            "variableType": "COLLECTED",
            "values": {
                "COLLECTED": [null],
                "EDITED": [null],
                "INPUTED": [null],
                "FORCED": [null],
                "PREVIOUS": [null]
            },
            "name": "ENDTIME",
            "componentRef": "timepicker_endTime"
        },
        {
            "variableType": "COLLECTED",
            "values": {
                "COLLECTED": [null],
                "EDITED": [null],
                "INPUTED": [null],
                "FORCED": [null],
                "PREVIOUS": [null]
            },
            "name": "MAINACTIVITY",
            "componentRef": "activityselecter_mainactivity"
        },
        {
            "variableType": "COLLECTED",
            "values": {
                "COLLECTED": [null],
                "EDITED": [null],
                "INPUTED": [null],
                "FORCED": [null],
                "PREVIOUS": [null]
            },
            "name": "GOAL",
            "componentRef": "goalselecter_goal"
        },
        {
            "variableType": "COLLECTED",
            "values": {
                "COLLECTED": [null],
                "EDITED": [null],
                "INPUTED": [null],
                "FORCED": [null],
                "PREVIOUS": [null]
            },
            "name": "WITHSECONDARYACTIVITY",
            "componentRef": "checkboxboolean_withsecondaryactivity"
        },
        {
            "variableType": "COLLECTED",
            "values": {
                "COLLECTED": [null],
                "EDITED": [null],
                "INPUTED": [null],
                "FORCED": [null],
                "PREVIOUS": [null]
            },
            "name": "SECONDARYACTIVITY",
            "componentRef": "checkboxone_secondaryactivity"
        },
        {
            "variableType": "COLLECTED",
            "values": {
                "COLLECTED": [null],
                "EDITED": [null],
                "INPUTED": [null],
                "FORCED": [null],
                "PREVIOUS": [null]
            },
            "name": "PLACE",
            "componentRef": "input_place"
        },
        {
            "variableType": "COLLECTED",
            "values": {
                "COLLECTED": [null],
                "EDITED": [null],
                "INPUTED": [null],
                "FORCED": [null],
                "PREVIOUS": [null]
            },
            "name": "WITHSOMEONE",
            "componentRef": "checkboxboolean_withsomeone"
        },
        {
            "variableType": "COLLECTED",
            "values": {
                "COLLECTED": [null],
                "EDITED": [null],
                "INPUTED": [null],
                "FORCED": [null],
                "PREVIOUS": [null]
            },
            "name": "COUPLE",
            "componentRef": "checkboxgroup_presentpeople"
        },
        {
            "variableType": "COLLECTED",
            "values": {
                "COLLECTED": [null],
                "EDITED": [null],
                "INPUTED": [null],
                "FORCED": [null],
                "PREVIOUS": [null]
            },
            "name": "PARENTS",
            "componentRef": "checkboxgroup_presentpeople"
        },
        {
            "variableType": "COLLECTED",
            "values": {
                "COLLECTED": [null],
                "EDITED": [null],
                "INPUTED": [null],
                "FORCED": [null],
                "PREVIOUS": [null]
            },
            "name": "CHILD",
            "componentRef": "checkboxgroup_presentpeople"
        },
        {
            "variableType": "COLLECTED",
            "values": {
                "COLLECTED": [null],
                "EDITED": [null],
                "INPUTED": [null],
                "FORCED": [null],
                "PREVIOUS": [null]
            },
            "name": "OTHERKNOWN",
            "componentRef": "checkboxgroup_presentpeople"
        },
        {
            "variableType": "COLLECTED",
            "values": {
                "COLLECTED": [null],
                "EDITED": [null],
                "INPUTED": [null],
                "FORCED": [null],
                "PREVIOUS": [null]
            },
            "name": "OTHER",
            "componentRef": "checkboxgroup_presentpeople"
        },
        {
            "variableType": "COLLECTED",
            "values": {
                "COLLECTED": [null],
                "EDITED": [null],
                "INPUTED": [null],
                "FORCED": [null],
                "PREVIOUS": [null]
            },
            "name": "WITHSCREEN",
            "componentRef": "checkboxboolean_withscreen"
        },
        {
            "variableType": "COLLECTED",
            "values": {
                "COLLECTED": null,
                "EDITED": null,
                "INPUTED": null,
                "FORCED": null,
                "PREVIOUS": null
            },
            "name": "WORKINGALLDAY",
            "componentRef": "checkboxgroup_daytype"
        },
        {
            "variableType": "COLLECTED",
            "values": {
                "COLLECTED": null,
                "EDITED": null,
                "INPUTED": null,
                "FORCED": null,
                "PREVIOUS": null
            },
            "name": "ISCLOSED",
            "componentRef": ""
        },
        {
            "variableType": "CALCULATED",
            "expression": "true",
            "name": "FILTER_RESULT_INPUTTEXT",
            "inFilter": "false"
        },
        {
            "variableType": "CALCULATED",
            "expression": "true",
            "name": "FILTER_RESULT_DATEPICKER",
            "inFilter": "false"
        }
    ],
    "components": [
        {
            "componentType": "Sequence",
            "hierarchy": {
                "sequence": { "id": "sequence_1", "page": "1" }
            },
            "conditionFilter": { "value": "true" },
            "id": "sequence_1",
            "page": "1",
            "label": ""
        },
        {
            "componentType": "Input",
            "bindingDependencies": ["FIRSTNAME"],
            "response": { "name": "FIRSTNAME" },
            "hierarchy": {
                "sequence": { "id": "sequence_1", "page": "1" }
            },
            "conditionFilter": { "value": "true" },
            "id": "inputtext_firstName",
            "page": "1",
            "label": "\"Qui êtes-vous ?\"",
            "placeholder": "Prénom",
            "mandatory": true,
            "maxLength": 100,
            "controls": [
                {
                    "criticality": "ERROR",
                    "errorMessage": {
                        "type": "VTL|MD",
                        "value": "\" La valeur doit être rempli.\""
                    },
                    "typeOfControl": "FORMAT",
                    "control": {
                        "type": "VTL",
                        "value": "not(isnull(FIRSTNAME)) and length(FIRSTNAME) >= 1"
                    },
                    "id": "kze792d8-formatBorneInfSup"
                }
            ]
        },
        {
            "componentType": "Datepicker",
            "bindingDependencies": ["SURVEYDATE"],
            "min": "1900-01-01",
            "max": "format-date(current-date(),'[Y0001]-[M01]-[D01]')",
            "dateFormat": "YYYY-MM-DD",
            "response": { "name": "SURVEYDATE" },
            "hierarchy": {
                "sequence": { "id": "sequence_1", "page": "1" }
            },
            "conditionFilter": { "value": "true" },
            "id": "datepicker_surveyDate",
            "page": "2",
            "label": "\"Quelle est la date du jour sélectionnée pour l'enquête ?\"",
            "mandatory": false,
            "controls": [
                {
                    "criticality": "ERROR",
                    "errorMessage": {
                        "type": "VTL|MD",
                        "value": "\" La valeur doit être rempli.\""
                    },
                    "typeOfControl": "FORMAT",
                    "control": {
                        "type": "VTL",
                        "value": "not(isnull(SURVEYDATE)) and length(SURVEYDATE) >= 1"
                    },
                    "id": "kze792d8-inputSurveyDate"
                }
            ]
        },
        {
            "id": "j6p0ti5h",
            "componentType": "Sequence",
            "page": "3",
            "label": "\"Debut\"",
            "conditionFilter": { "value": "true", "type": "VTL" },
            "hierarchy": {
                "sequence": {
                    "id": "j6p0ti5h",
                    "page": "3",
                    "label": { "value": "\"Debut\"", "type": "VTL|MD" }
                }
            }
        },
        {
            "id": "law89hhb",
            "componentType": "Loop",
            "page": "4",
            "maxPage": "9",
            "depth": 1,
            "paginatedLoop": true,
            "conditionFilter": { "value": "true" },
            "bindingDependencies": [
                "STARTTIME",
                "ENDTIME",
                "MAINACTIVITY",
                "WITHSECONDARYACTIVITY",
                "SECONDARYACTIVITY",
                "PLACE",
                "WITHSOMEONE",
                "COUPLE",
                "PARENTS",
                "CHILD",
                "OTHERKNOWN",
                "OTHER",
                "WITHSCREEN"
            ],
            "loopDependencies": [],
            "iterations": { "value": "1", "type": "VTL" },
            "components": [
                {
                    "componentType": "Sequence",
                    "hierarchy": {
                        "sequence": {
                            "id": "law86mv7",
                            "page": "4.1",
                            "label": "\"I - \" || \"Sequence\""
                        }
                    },
                    "conditionFilter": { "value": "true" },
                    "id": "law86mv7",
                    "page": "4.1",
                    "label": "\"I - \" || \"Sequence\""
                },
                {
                    "componentType": "Timepicker",
                    "bindingDependencies": ["STARTTIME"],
                    "response": { "name": "STARTTIME" },
                    "hierarchy": {
                        "sequence": {
                            "id": "law86mv7",
                            "page": "4.1",
                            "label": "\"I - \" || \"Sequence\""
                        }
                    },
                    "conditionFilter": { "value": "true" },
                    "id": "timepicker_startTime",
                    "page": "4.2",
                    "label": "\"Heure de début\"",
                    "mandatory": false,
                    "maxLength": 249
                },
                {
                    "componentType": "Timepicker",
                    "bindingDependencies": ["ENDTIME"],
                    "response": { "name": "ENDTIME" },
                    "hierarchy": {
                        "sequence": {
                            "id": "law86mv7",
                            "page": "4.1",
                            "label": "\"I - \" || \"Sequence\""
                        }
                    },
                    "conditionFilter": { "value": "true" },
                    "id": "timepicker_endTime",
                    "page": "4.2",
                    "label": "\"Heure de fin\"",
                    "mandatory": false,
                    "maxLength": 249
                },
                {
                    "componentType": "ActivitySelecter",
                    "bindingDependencies": ["MAINACTIVITY"],
                    "response": { "name": "MAINACTIVITY" },
                    "hierarchy": {
                        "sequence": {
                            "id": "law86mv7",
                            "page": "4.1",
                            "label": "\"I - \" || \"Sequence\""
                        }
                    },
                    "conditionFilter": { "value": "true" },
                    "id": "activityselecter_mainactivity",
                    "page": "4.3",
                    "label": "\"Que faisiez-vous ?\"",
                    "mandatory": false
                },
                {
                    "componentType": "CheckboxBoolean",
                    "bindingDependencies": ["WITHSECONDARYACTIVITY"],
                    "response": { "name": "WITHSECONDARYACTIVITY" },
                    "hierarchy": {
                        "sequence": {
                            "id": "law86mv7",
                            "page": "4.1",
                            "label": "\"I - \" || \"Sequence\""
                        }
                    },
                    "conditionFilter": { "value": "true" },
                    "id": "checkboxboolean_withsecondaryactivity",
                    "page": "4.4",
                    "label": "\"Faisiez-vous autre chose en même temps ?\"",
                    "mandatory": false
                },
                {
                    "componentType": "IconGridCheckBoxOne",
                    "bindingDependencies": ["PLACE"],
                    "response": { "name": "PLACE" },
                    "hierarchy": {
                        "sequence": {
                            "id": "law86mv7",
                            "page": "4.1",
                            "label": "\"I - \" || \"Sequence\""
                        }
                    },
                    "conditionFilter": { "value": "true" },
                    "id": "input_place",
                    "page": "4.5",
                    "label": "\"Où étiez-vous ?\"",
                    "mandatory": false,
                    "options": [
                        {
                            "label": "\"Chez soi (yc appartement étudiant si différent du domicile familial)\"",
                            "value": "11"
                        },
                        { "label": "\"Lieu de travail ou d’études\"", "value": "12" },
                        { "label": "\"Résidence secondaire, location de vacances\"", "value": "14" },
                        { "label": "\"Restaurant, café, bar\"", "value": "15" },
                        {
                            "label": "\"Chez une autre personne (ami, voisin, famille…)\"",
                            "value": "13"
                        },
                        { "label": "\"Autre (commerces, loisirs, dans la rue…)\"", "value": "16" }
                    ]
                },
                {
                    "componentType": "CheckboxBoolean",
                    "bindingDependencies": ["WITHSOMEONE"],
                    "response": { "name": "WITHSOMEONE" },
                    "hierarchy": {
                        "sequence": {
                            "id": "law86mv7",
                            "page": "4.1",
                            "label": "\"I - \" || \"Sequence\""
                        }
                    },
                    "conditionFilter": { "value": "true" },
                    "id": "checkboxboolean_withsomeone",
                    "page": "4.6",
                    "label": "\"Etiez-vous en compagnie de quelqu'un ?\"",
                    "mandatory": false
                },
                {
                    "componentType": "CheckboxBoolean",
                    "bindingDependencies": ["WITHSCREEN"],
                    "response": { "name": "WITHSCREEN" },
                    "hierarchy": {
                        "sequence": {
                            "id": "law86mv7",
                            "page": "4.1",
                            "label": "\"I - \" || \"Sequence\""
                        }
                    },
                    "conditionFilter": { "value": "true" },
                    "id": "checkboxboolean_withscreen",
                    "page": "4.7",
                    "label": "\"Avez-vous utilisé un ordinateur, un smartphone, une tablette ou un autre objet connecté à internet ?\"",
                    "mandatory": false
                },
                {
                    "componentType": "IconGridCheckBoxOne",
                    "bindingDependencies": ["GOAL"],
                    "response": { "name": "GOAL" },
                    "hierarchy": {
                        "sequence": {
                            "id": "law86mv7",
                            "page": "4.1",
                            "label": "\"I - \" || \"Sequence\""
                        }
                    },
                    "conditionFilter": { "value": "true" },
                    "id": "goalselecter_goal",
                    "page": "4.8",
                    "label": "\"Dans quel but avez-vous fait cette activité ?\"",
                    "mandatory": false,
                    "options": [
                        { "label": "\"Personnel, pour son ménage\"", "value": "1" },
                        { "label": "\"Professionnel\"", "value": "2" },
                        { "label": "\"Aide à un autre ménage\"", "value": "3" },
                        { "label": "\"Bénévole, pour une association\"", "value": "4" }
                    ]
                },
                {
                    "componentType": "CheckboxOneEdt",
                    "bindingDependencies": ["SECONDARYACTIVITY"],
                    "response": { "name": "SECONDARYACTIVITY" },
                    "hierarchy": {
                        "sequence": {
                            "id": "law86mv7",
                            "page": "4.1",
                            "label": "\"I - \" || \"Sequence\""
                        }
                    },
                    "options": [
                        {
                            "label": "\"Écouter la radio, des podcasts ou de la musique\"",
                            "value": "636/637/638"
                        },
                        {
                            "label": "\"Regarder la télévision, des DVD, des vidéos en ligne\"",
                            "value": "634,635"
                        },
                        { "label": "Conversation", "value": "521" },
                        {
                            "label": "\"Surf sur Internet, visite de sites pour s'informer (hors journaux)\"",
                            "value": "673"
                        },
                        {
                            "label": "\"Publier ou surfer sur les médias sociaux (Facebook, Instagram, Twitter, Tumblr, LinkedIn, ...)\"",
                            "value": "674"
                        },
                        { "label": "\"Lecture de journaux, revues\"", "value": "633" },
                        { "label": "\"Lecture de livres\"", "value": "632" },
                        { "label": "\"Repas\"", "value": "todetermine" },
                        { "label": "\"Travail professionnel\"", "value": "211" },
                        { "label": "\"Se détendre, fumer\"", "value": "641" },
                        { "label": "\"Conversations avec les enfants, lectures\"", "value": "422" },
                        { "label": "\"Repas, douche, habillage des enfants\"", "value": "411" },
                        { "label": "\"Surveiller les devoirs des enfants\"", "value": "421" }
                    ],
                    "conditionFilter": { "value": "true" },
                    "id": "checkboxone_secondaryactivity",
                    "page": "4.9",
                    "label": "\"Que faisiez-vous en même temps ?\"",
                    "mandatory": false
                },
                {
                    "componentType": "CheckboxGroupEdt",
                    "bindingDependencies": ["COUPLE", "PARENTS", "CHILD", "OTHERKNOWN", "OTHER"],
                    "responses": [
                        {
                            "response": {
                                "name": "COUPLE"
                            },
                            "id": "1",
                            "label": "\"Votre conjoint\""
                        },
                        {
                            "response": {
                                "name": "PARENTS"
                            },
                            "id": "2",
                            "label": "\"Votre Mère, votre Père\""
                        },
                        {
                            "response": {
                                "name": "CHILD"
                            },
                            "id": "3",
                            "label": "\"Enfant(s) du ménage\""
                        },
                        {
                            "response": {
                                "name": "OTHERKNOWN"
                            },
                            "id": "4",
                            "label": "\"Autre(s) personne(s) du ménage\""
                        },
                        {
                            "response": {
                                "name": "OTHER"
                            },
                            "id": "5",
                            "label": "\"Autre(s) Personne(s) que vous connaissez\""
                        }
                    ],
                    "hierarchy": {
                        "sequence": {
                            "id": "law86mv7",
                            "page": "4.1",
                            "label": "\"I - \" || \"Sequence\""
                        }
                    },
                    "conditionFilter": { "value": "true" },
                    "id": "checkboxgroup_presentpeople",
                    "page": "4.10",
                    "label": "\"En présence de qui étiez-vous ?\"",
                    "mandatory": false
                }
            ]
        },
        {
            "componentType": "CheckboxGroupEdt",
            "bindingDependencies": ["WORKINGALLDAY"],
            "responses": [
                {
                    "response": {
                        "name": "WORKINGALLDAY"
                    },
                    "id": "5",
                    "label": "\"Journée normale de travail\""
                }
            ],
            "hierarchy": {
                "sequence": {
                    "id": "j6p0ti5h",
                    "page": "5"
                }
            },
            "conditionFilter": { "value": "true" },
            "id": "checkboxgroup_daytype",
            "page": "5",
            "label": "\"De quel type de journée s’agissait-il ?\"",
            "mandatory": false
        },
        {
            "id": "End",
            "componentType": "Sequence",
            "page": "6",
            "label": { "value": "\"End\"", "type": "VTL|MD" },
            "conditionFilter": { "value": "true" },
            "hierarchy": {
                "sequence": {
                    "id": "End",
                    "page": "6",
                    "label": { "value": "\"End\"", "type": "VTL|MD" }
                }
            }
        }
    ]
}
